odoo10_addon_account_invoice_pricelist_sale-10.0.1.0.0-py2.7-nspkg.pth
odoo/addons/account_invoice_pricelist_sale/README.rst
odoo/addons/account_invoice_pricelist_sale/__init__.py
odoo/addons/account_invoice_pricelist_sale/__manifest__.py
odoo/addons/account_invoice_pricelist_sale/i18n/ca.po
odoo/addons/account_invoice_pricelist_sale/i18n/de.po
odoo/addons/account_invoice_pricelist_sale/i18n/el_GR.po
odoo/addons/account_invoice_pricelist_sale/i18n/es.po
odoo/addons/account_invoice_pricelist_sale/i18n/es_VE.po
odoo/addons/account_invoice_pricelist_sale/i18n/fi.po
odoo/addons/account_invoice_pricelist_sale/i18n/fr.po
odoo/addons/account_invoice_pricelist_sale/i18n/hr.po
odoo/addons/account_invoice_pricelist_sale/i18n/hr_HR.po
odoo/addons/account_invoice_pricelist_sale/i18n/hu.po
odoo/addons/account_invoice_pricelist_sale/i18n/it.po
odoo/addons/account_invoice_pricelist_sale/i18n/nl.po
odoo/addons/account_invoice_pricelist_sale/i18n/nl_NL.po
odoo/addons/account_invoice_pricelist_sale/i18n/pt.po
odoo/addons/account_invoice_pricelist_sale/i18n/pt_BR.po
odoo/addons/account_invoice_pricelist_sale/i18n/ro.po
odoo/addons/account_invoice_pricelist_sale/i18n/sl.po
odoo/addons/account_invoice_pricelist_sale/i18n/tr.po
odoo/addons/account_invoice_pricelist_sale/i18n/tr_TR.po
odoo/addons/account_invoice_pricelist_sale/i18n/vi_VN.po
odoo/addons/account_invoice_pricelist_sale/i18n/zh_CN.po
odoo/addons/account_invoice_pricelist_sale/models/__init__.py
odoo/addons/account_invoice_pricelist_sale/models/sale_order.py
odoo/addons/account_invoice_pricelist_sale/static/src/description/icon.png
odoo10_addon_account_invoice_pricelist_sale-10.0.1.0.0.dist-info/DESCRIPTION.rst
odoo10_addon_account_invoice_pricelist_sale-10.0.1.0.0.dist-info/METADATA
odoo10_addon_account_invoice_pricelist_sale-10.0.1.0.0.dist-info/RECORD
odoo10_addon_account_invoice_pricelist_sale-10.0.1.0.0.dist-info/WHEEL
odoo10_addon_account_invoice_pricelist_sale-10.0.1.0.0.dist-info/metadata.json
odoo10_addon_account_invoice_pricelist_sale-10.0.1.0.0.dist-info/namespace_packages.txt
odoo10_addon_account_invoice_pricelist_sale-10.0.1.0.0.dist-info/top_level.txt
